perceptilabs/__init__.py
perceptilabs/__main__.py
perceptilabs/app_variables.json
perceptilabs/auth.cpython-38-x86_64-linux-gnu.so
perceptilabs/call_context.cpython-38-x86_64-linux-gnu.so
perceptilabs/createDataObject.cpython-38-x86_64-linux-gnu.so
perceptilabs/datasets_interface.cpython-38-x86_64-linux-gnu.so
perceptilabs/hardware.cpython-38-x86_64-linux-gnu.so
perceptilabs/inference_interface.cpython-38-x86_64-linux-gnu.so
perceptilabs/issues.cpython-38-x86_64-linux-gnu.so
perceptilabs/license_checker.cpython-38-x86_64-linux-gnu.so
perceptilabs/mainServer.cpython-38-x86_64-linux-gnu.so
perceptilabs/main_setup.cpython-38-x86_64-linux-gnu.so
perceptilabs/models_interface.cpython-38-x86_64-linux-gnu.so
perceptilabs/preprocessing_interface.cpython-38-x86_64-linux-gnu.so
perceptilabs/rygg.cpython-38-x86_64-linux-gnu.so
perceptilabs/serving_interface.cpython-38-x86_64-linux-gnu.so
perceptilabs/settings.cpython-38-x86_64-linux-gnu.so
perceptilabs/testing_interface.cpython-38-x86_64-linux-gnu.so
perceptilabs/training_interface.cpython-38-x86_64-linux-gnu.so
perceptilabs/utils.cpython-38-x86_64-linux-gnu.so
perceptilabs/zipfile_serving.cpython-38-x86_64-linux-gnu.so
perceptilabs/api/__init__.py
perceptilabs/api/base.cpython-38-x86_64-linux-gnu.so
perceptilabs/automation/__init__.py
perceptilabs/automation/utils.cpython-38-x86_64-linux-gnu.so
perceptilabs/automation/autosettings/__init__.py
perceptilabs/automation/autosettings/base.cpython-38-x86_64-linux-gnu.so
perceptilabs/automation/autosettings/rules.cpython-38-x86_64-linux-gnu.so
perceptilabs/automation/autosettings/utils.cpython-38-x86_64-linux-gnu.so
perceptilabs/automation/modelrecommender/__init__.py
perceptilabs/automation/modelrecommender/base.cpython-38-x86_64-linux-gnu.so
perceptilabs/automation/modelrecommender/decoders/__init__.py
perceptilabs/automation/modelrecommender/decoders/base.cpython-38-x86_64-linux-gnu.so
perceptilabs/automation/modelrecommender/decoders/categorical.cpython-38-x86_64-linux-gnu.so
perceptilabs-0.13.21.dist-info/METADATA
perceptilabs-0.13.21.dist-info/WHEEL
perceptilabs-0.13.21.dist-info/entry_points.txt
perceptilabs-0.13.21.dist-info/top_level.txt
perceptilabs-0.13.21.dist-info/RECORD
