Metadata-Version: 2.1
Name: perceptilabs
Version: 0.13.21
Home-page: https://perceptilabs.com
Author: PerceptiLabs
Author-email: contact@perceptilabs.com
License: Custom Proprietary License
Requires-Python: >=3.7,<3.9
Requires-Dist: aiohttp (==3.7.4)
Requires-Dist: aiofiles (>=0.8.0)
Requires-Dist: astor (>=0.8.0)
Requires-Dist: azure-eventhub (==5.1.0)
Requires-Dist: azure-storage-blob (==12.6.0)
Requires-Dist: boltons (>=19.3.0)
Requires-Dist: boto3 (>=1.9.233)
Requires-Dist: boto (>=2.49.0)
Requires-Dist: cachetools (==5.0.0)
Requires-Dist: celery (==5.1.2)
Requires-Dist: cryptography (==36.0.1)
Requires-Dist: dask[array] (==2.6.0)
Requires-Dist: dask[dataframe] (==2.6.0)
Requires-Dist: fastapi (==0.68.0)
Requires-Dist: filelock (==3.3.2)
Requires-Dist: flask-compress (==1.9.0)
Requires-Dist: flask-cors (>=3.0.10)
Requires-Dist: Flask (==2.0.2)
Requires-Dist: flower (>=1.0.0)
Requires-Dist: fsspec (>=0.6.0)
Requires-Dist: gputil (>=1.4.0)
Requires-Dist: gradio (<=2.9.4,>=2.3.0)
Requires-Dist: gym-unity (>=0.20.0)
Requires-Dist: h5py (==3.1.0)
Requires-Dist: jinja2 (<=3.0.3,>=2.10.3)
Requires-Dist: keras2onnx (==1.7.0)
Requires-Dist: keras-unet-collection (==0.1.10)
Requires-Dist: matplotlib (<=3.4.2)
Requires-Dist: mixpanel (==4.7.0)
Requires-Dist: numpy (<=1.19.2,>=1.18.5)
Requires-Dist: onnx (==1.9.0)
Requires-Dist: pandas (>=0.25.0)
Requires-Dist: pillow (>=7.0.0)
Requires-Dist: psutil (>=5.6.3)
Requires-Dist: pydantic (>=1.6.1)
Requires-Dist: PyJWT (>=1.7.1)
Requires-Dist: retrying (>=1.3.3)
Requires-Dist: redis (==3.5.3)
Requires-Dist: requests (==2.27.1)
Requires-Dist: scikit-image (==0.17.2)
Requires-Dist: scikit-learn (>=0.22.1)
Requires-Dist: scipy (>=1.3.0)
Requires-Dist: shap (>=0.40.0)
Requires-Dist: six (>=1.14.0)
Requires-Dist: tensorflow-addons (==0.13.0)
Requires-Dist: tensorflow-hub (==0.12.0)
Requires-Dist: tensorflow (==2.5.0)
Requires-Dist: tf2onnx (==1.7.2)
Requires-Dist: uvicorn (==0.15.0)
Requires-Dist: waitress (==2.0.0)
Requires-Dist: websockets (>=8.1)
Requires-Dist: Werkzeug (<=2.0.3)
Requires-Dist: asgiref (>=3.3.2)
Requires-Dist: blessings (>=1.7)
Requires-Dist: celery (>=4.4.2)
Requires-Dist: certifi (>=2020.6.20)
Requires-Dist: chardet (>=3.0.4)
Requires-Dist: cryptography (>=2.8)
Requires-Dist: curtsies (>=0.3.1)
Requires-Dist: Deprecated (>=1.2.10)
Requires-Dist: django-cors-headers (>=3.2.1)
Requires-Dist: django-extensions (>=3.1.3)
Requires-Dist: django-http-exceptions (>=1.3.1)
Requires-Dist: django-model-utils (>=4.1.1)
Requires-Dist: django-request-logging (>0.7.2)
Requires-Dist: Django (==3.2)
Requires-Dist: djangorestframework (>=3.11.1)
Requires-Dist: drf-jwt (~=1.13.3)
Requires-Dist: gitdb (>=4.0.5)
Requires-Dist: GitPython (>=3.1.8)
Requires-Dist: greenlet (>=0.4.15)
Requires-Dist: idna (>=2.10)
Requires-Dist: importlib-metadata (>=1.7.0)
Requires-Dist: markdown (>=3.2.1)
Requires-Dist: more-itertools (>=8.9.0)
Requires-Dist: oauthlib (>=3.0.2)
Requires-Dist: packaging (>=20.4)
Requires-Dist: pathvalidate (>=2.5.0)
Requires-Dist: psycopg2-binary (>=2.8.5)
Requires-Dist: PyGithub (>=1.53)
Requires-Dist: pygments (>=2.6.1)
Requires-Dist: pyparsing (>=2.4.7)
Requires-Dist: python-dateutil (>=2.8.1)
Requires-Dist: pytz (>=2020.1)
Requires-Dist: redis (>=3.5.3)
Requires-Dist: requests-oauthlib (>=1.2.0)
Requires-Dist: Send2Trash (>=1.5.0)
Requires-Dist: smmap (>=3.0.4)
Requires-Dist: sqlparse (>=0.3.1)
Requires-Dist: tblib
Requires-Dist: urllib3 (==1.25.10)
Requires-Dist: wcwidth (>=0.1.9)
Requires-Dist: zipp (>=3.1.0)
Requires-Dist: asgiref (>=3.2.10)
Requires-Dist: Django (>=3.1)
Requires-Dist: django-request-logging (>=0.7.2)
Requires-Dist: requests (>=2.24.0)
Requires-Dist: websocket-client (>=1.1.0)
Requires-Dist: opencv-python ; platform_system != "Darwin"
Requires-Dist: opencv-python (>=4.5.4.60) ; platform_system == "Darwin"
Requires-Dist: sentry-sdk (>=1.5.2) ; platform_system == "Darwin"
Requires-Dist: pyobjc (<=8.0) ; platform_system == "Darwin" and python_version <= "3.8"
Requires-Dist: pyobjc ; platform_system == "Darwin" and python_version > "3.8"
Requires-Dist: sentry-sdk (>=1.5.2) ; platform_system == "Linux"
Requires-Dist: colorama (==0.4.3) ; platform_system == "Windows"
Requires-Dist: sentry-sdk (>=1.5.2) ; platform_system == "Windows"
Requires-Dist: pypiwin32 (>=223) ; platform_system == "Windows"
